pandasgeo/__init__.py
pandasgeo/core.py
pandasgeo/image.png
pandasgeo/utils.py
pandasgeo-0.0.6.dist-info/licenses/LICENSE
pandasgeo-0.0.6.dist-info/METADATA
pandasgeo-0.0.6.dist-info/WHEEL
pandasgeo-0.0.6.dist-info/top_level.txt
pandasgeo-0.0.6.dist-info/RECORD
