Metadata-Version: 2.4
Name: pandasgeo
Version: 0.0.6
Summary: A powerful Python library for geospatial data processing, analysis and conversion - integrating pandas with GIS operations
Author-email: Non-existent987 <jiaqi0425_000@163.com>
License: MIT License
Project-URL: Homepage, https://github.com/Non-existent987/pandasgeo
Project-URL: Bug Tracker, https://github.com/Non-existent987/pandasgeo/issues
Project-URL: Repository, https://github.com/Non-existent987/pandasgeo.git
Keywords: gis,geospatial,pandas,geopandas,shapefile,kml,geojson,spatial-analysis,geographic,geometry,mapping
Classifier: Programming Language :: Python :: 3
Classifier: License :: OSI Approved :: MIT License
Classifier: Operating System :: OS Independent
Classifier: Topic :: Scientific/Engineering :: GIS
Requires-Python: >=3.7
License-File: LICENSE
Requires-Dist: geopandas
Requires-Dist: pandas
Requires-Dist: numpy
Requires-Dist: shapely
Requires-Dist: simplekml
Requires-Dist: pyshp
Requires-Dist: geographiclib
Requires-Dist: kml2geojson
Requires-Dist: scipy
Requires-Dist: pyproj
Dynamic: license-file
